fds/__init__.py
fds/sdk/__init__.py
fds/sdk/IRNCustomSymbols/__init__.py
fds/sdk/IRNCustomSymbols/api_client.py
fds/sdk/IRNCustomSymbols/configuration.py
fds/sdk/IRNCustomSymbols/exceptions.py
fds/sdk/IRNCustomSymbols/model_utils.py
fds/sdk/IRNCustomSymbols/rest.py
fds/sdk/IRNCustomSymbols/api/__init__.py
fds/sdk/IRNCustomSymbols/api/custom_symbols___relationships_api.py
fds/sdk/IRNCustomSymbols/api/custom_symbols_api.py
fds/sdk/IRNCustomSymbols/api/hybrid_symbols_api.py
fds/sdk/IRNCustomSymbols/apis/__init__.py
fds/sdk/IRNCustomSymbols/model/__init__.py
fds/sdk/IRNCustomSymbols/model/create_custom_symbol_custom_field_value_dto.py
fds/sdk/IRNCustomSymbols/model/create_custom_symbol_dto.py
fds/sdk/IRNCustomSymbols/model/create_standard_symbol_metadata_dto.py
fds/sdk/IRNCustomSymbols/model/custom_symbol_address_dto.py
fds/sdk/IRNCustomSymbols/model/custom_symbol_contact.py
fds/sdk/IRNCustomSymbols/model/custom_symbol_custom_field_value_dto.py
fds/sdk/IRNCustomSymbols/model/custom_symbol_dto.py
fds/sdk/IRNCustomSymbols/model/custom_symbol_sub_type_summary_dto.py
fds/sdk/IRNCustomSymbols/model/custom_symbol_type_summary_dto.py
fds/sdk/IRNCustomSymbols/model/instrument_dto.py
fds/sdk/IRNCustomSymbols/model/new_item_dto.py
fds/sdk/IRNCustomSymbols/model/operation.py
fds/sdk/IRNCustomSymbols/model/operation_type.py
fds/sdk/IRNCustomSymbols/model/problem_details.py
fds/sdk/IRNCustomSymbols/model/record_preview_dto.py
fds/sdk/IRNCustomSymbols/model/standard_symbol_dto.py
fds/sdk/IRNCustomSymbols/model/symbol_id_name_dto.py
fds/sdk/IRNCustomSymbols/model/symbol_relationship_dto.py
fds/sdk/IRNCustomSymbols/model/symbol_relationship_save_dto.py
fds/sdk/IRNCustomSymbols/model/symbol_relationship_update_dto.py
fds/sdk/IRNCustomSymbols/model/symbols_relationship_id_name_dto.py
fds/sdk/IRNCustomSymbols/model/symbols_relationship_type.py
fds/sdk/IRNCustomSymbols/models/__init__.py
fds.sdk.IRNCustomSymbols-1.1.1.dist-info/LICENSE
fds.sdk.IRNCustomSymbols-1.1.1.dist-info/METADATA
fds.sdk.IRNCustomSymbols-1.1.1.dist-info/WHEEL
fds.sdk.IRNCustomSymbols-1.1.1.dist-info/top_level.txt
fds.sdk.IRNCustomSymbols-1.1.1.dist-info/RECORD
